Metadata-Version: 2.1
Name: cherche
Version: 2.1.1
Summary: Neural Search
Home-page: https://github.com/raphaelsty/cherche
Download-URL: https://github.com/user/cherche/archive/v_01.tar.gz
Author: Raphael Sourty
Author-email: raphael.sourty@gmail.com
License: MIT
Keywords: neural search,information retrieval,question answering,semantic search
Classifier: Programming Language :: Python :: 3
Classifier: License :: OSI Approved :: MIT License
Classifier: Operating System :: OS Independent
Requires-Python: >=3.6
License-File: LICENSE
Requires-Dist: numpy>=1.23.5
Requires-Dist: scikit-learn>=1.1.2
Requires-Dist: lunr>=0.6.2
Requires-Dist: rapidfuzz>=3.0.0
Requires-Dist: flashtext>=2.7
Requires-Dist: tqdm>=4.62.3
Requires-Dist: scipy>=1.7.3
Requires-Dist: lenlp==1.0.5
Provides-Extra: cpu
Requires-Dist: numpy>=1.23.5; extra == "cpu"
Requires-Dist: scikit-learn>=1.1.2; extra == "cpu"
Requires-Dist: lunr>=0.6.2; extra == "cpu"
Requires-Dist: rapidfuzz>=3.0.0; extra == "cpu"
Requires-Dist: flashtext>=2.7; extra == "cpu"
Requires-Dist: tqdm>=4.62.3; extra == "cpu"
Requires-Dist: scipy>=1.7.3; extra == "cpu"
Requires-Dist: lenlp==1.0.5; extra == "cpu"
Requires-Dist: sentence-transformers>=2.2.2; extra == "cpu"
Requires-Dist: faiss-cpu>=1.7.4; extra == "cpu"
Provides-Extra: gpu
Requires-Dist: numpy>=1.23.5; extra == "gpu"
Requires-Dist: scikit-learn>=1.1.2; extra == "gpu"
Requires-Dist: lunr>=0.6.2; extra == "gpu"
Requires-Dist: rapidfuzz>=3.0.0; extra == "gpu"
Requires-Dist: flashtext>=2.7; extra == "gpu"
Requires-Dist: tqdm>=4.62.3; extra == "gpu"
Requires-Dist: scipy>=1.7.3; extra == "gpu"
Requires-Dist: lenlp==1.0.5; extra == "gpu"
Requires-Dist: sentence-transformers>=2.2.2; extra == "gpu"
Requires-Dist: faiss-gpu>=1.7.4; extra == "gpu"
Provides-Extra: dev
Requires-Dist: numpy>=1.23.5; extra == "dev"
Requires-Dist: scikit-learn>=1.1.2; extra == "dev"
Requires-Dist: lunr>=0.6.2; extra == "dev"
Requires-Dist: rapidfuzz>=3.0.0; extra == "dev"
Requires-Dist: flashtext>=2.7; extra == "dev"
Requires-Dist: tqdm>=4.62.3; extra == "dev"
Requires-Dist: scipy>=1.7.3; extra == "dev"
Requires-Dist: lenlp==1.0.5; extra == "dev"
Requires-Dist: sentence-transformers>=2.2.2; extra == "dev"
Requires-Dist: faiss-cpu>=1.7.4; extra == "dev"
Requires-Dist: numpydoc>=1.4.0; extra == "dev"
Requires-Dist: mkdocs_material>=8.3.5; extra == "dev"
Requires-Dist: mkdocs-awesome-pages-plugin>=2.7.0; extra == "dev"
Requires-Dist: mkdocs-jupyter>=0.21.0; extra == "dev"
Requires-Dist: pytest-cov>=4.0.0; extra == "dev"
Requires-Dist: pytest>=7.3.1; extra == "dev"
Requires-Dist: isort>=5.12.0; extra == "dev"
Requires-Dist: ipywidgets>=8.0.6; extra == "dev"
